monitorcontrol/__init__.py
monitorcontrol/__main__.py
monitorcontrol/monitorcontrol.py
monitorcontrol/vcp/__init__.py
monitorcontrol/vcp/vcp_abc.py
monitorcontrol/vcp/vcp_codes.py
monitorcontrol/vcp/vcp_linux.py
monitorcontrol/vcp/vcp_windows.py
monitorcontrol-4.1.0.dist-info/licenses/LICENSE
monitorcontrol-4.1.0.dist-info/METADATA
monitorcontrol-4.1.0.dist-info/WHEEL
monitorcontrol-4.1.0.dist-info/entry_points.txt
monitorcontrol-4.1.0.dist-info/top_level.txt
monitorcontrol-4.1.0.dist-info/RECORD
