Metadata-Version: 2.4
Name: monitorcontrol
Version: 4.1.0
Summary: Monitor controls using MCCS over DDC-CI.
Author-email: Alex Martens <alex+monitorcontrol@thinglab.org>
License-Expression: MIT
Project-URL: Repository, https://github.com/newAM/monitorcontrol
Project-URL: Documentation, https://newam.github.io/monitorcontrol
Project-URL: Changelog, https://github.com/newAM/monitorcontrol/blob/main/CHANGELOG.md
Project-URL: Issues, https://github.com/newAM/monitorcontrol/issues
Requires-Python: >=3.9
License-File: LICENSE
Requires-Dist: pyudev>=0.23.3; sys_platform != "win32"
Dynamic: license-file
